fastapi_gino_viewsets/__init__.py
fastapi_gino_viewsets/base_config.py
fastapi_gino_viewsets/dynamic_methods.py
fastapi_gino_viewsets/mixins.py
fastapi_gino_viewsets/router.py
fastapi_gino_viewsets/schema_factory.py
fastapi_gino_viewsets/schemas.py
fastapi_gino_viewsets/utils.py
fastapi_gino_viewsets/viewsets.py
tests/__init__.py
tests/conftest.py
tests/factory.py
tests/models.py
tests/test_base_schemas.py
tests/test_gino_model_meta.py
tests/test_mixins_viewsets.py
tests/test_schema_factory.py
tests/test_utils.py
tests/test_viewsets_inheritance.py
tests/test_wrapper_schema.py
tests/utils.py
fastapi_gino_viewsets-0.1.0b6.dist-info/LICENSE.txt
fastapi_gino_viewsets-0.1.0b6.dist-info/METADATA
fastapi_gino_viewsets-0.1.0b6.dist-info/WHEEL
fastapi_gino_viewsets-0.1.0b6.dist-info/top_level.txt
fastapi_gino_viewsets-0.1.0b6.dist-info/RECORD
