Metadata-Version: 2.1
Name: fastapi-gino-viewsets
Version: 0.1.0b6
Summary: FastApi Gino ViewSets
Home-page: UNKNOWN
Author: Basalex (Alexander Baskakov)
Author-email: <alexanderbaskakov@mail.ru>
License: UNKNOWN
Project-URL: Source, https://github.com/Basalex/fastapi-gino-viewsets
Keywords: python,fastapi,gino,viewsets,pydantic,models
Platform: UNKNOWN
Classifier: Development Status :: 4 - Beta
Classifier: Intended Audience :: Developers
Classifier: Programming Language :: Python :: 3
Classifier: Operating System :: Unix
Classifier: Operating System :: MacOS :: MacOS X
Classifier: Operating System :: Microsoft :: Windows
Requires-Dist: fastapi
Requires-Dist: gino
Requires-Dist: ginodantic
